flake8_plugin_utils/__init__.py
flake8_plugin_utils/plugin.py
flake8_plugin_utils/utils/__init__.py
flake8_plugin_utils/utils/_internal.py
flake8_plugin_utils/utils/assertions.py
flake8_plugin_utils/utils/constants.py
flake8_plugin_utils/utils/equiv_nodes.py
flake8_plugin_utils-1.3.0.dist-info/LICENSE
flake8_plugin_utils-1.3.0.dist-info/WHEEL
flake8_plugin_utils-1.3.0.dist-info/METADATA
flake8_plugin_utils-1.3.0.dist-info/RECORD
