Metadata-Version: 2.1
Name: flake8-plugin-utils
Version: 1.3.0
Summary: The package provides base classes and utils for flake8 plugin writing
Home-page: https://pypi.org/project/flake8-plugin-utils
License: MIT
Keywords: flake8,plugin,utils
Author: Afonasev Evgeniy
Author-email: ea.afonasev@gmail.com
Requires-Python: >=3.6,<4.0
Classifier: License :: OSI Approved :: MIT License
Classifier: Programming Language :: Python :: 3
Classifier: Programming Language :: Python :: 3.6
Classifier: Programming Language :: Python :: 3.7
Classifier: Programming Language :: Python :: 3.8
Project-URL: Repository, https://github.com/afonasev/flake8-plugin-utils
